oven/__init__.py
oven/__main__.py
oven/cli.py
oven/oven/__init__.py
oven/oven/config.py
oven/oven/errors.py
oven/oven/scripts.py
oven/oven/site.py
oven/oven/theme.py
oven/oven/trans.py
oven/oven/urls.py
oven/oven/utils.py
oven/oven/internal_extensions/__init__.py
oven/oven/internal_extensions/oven_urls.py
oven/oven/internal_filters/__init__.py
oven/oven/internal_filters/get_text.py
oven/oven/internal_filters/get_url.py
oven/oven/internal_scripts/__init__.py
oven/oven/internal_scripts/archive.py
oven/oven/internal_scripts/assets.py
oven/oven/internal_scripts/clean.py
oven/oven/internal_scripts/make_index.py
oven/oven/internal_scripts/robots.py
oven/oven/internal_scripts/sitemap.py
oven_cli-1.0.dist-info/LICENSE
oven_cli-1.0.dist-info/METADATA
oven_cli-1.0.dist-info/WHEEL
oven_cli-1.0.dist-info/entry_points.txt
oven_cli-1.0.dist-info/top_level.txt
oven_cli-1.0.dist-info/RECORD
