Metadata-Version: 2.1
Name: oven-cli
Version: 1.0
Summary: A static site generator with markdown support
Home-page: https://github.com/ktxyz/oven
Author: Kamil Tokarski
Author-email: kamil@tokarski.xyz
Classifier: Programming Language :: Python :: 3
Classifier: License :: OSI Approved :: MIT License
Classifier: Operating System :: OS Independent
Requires-Python: >=3.6
License-File: LICENSE
Requires-Dist: jinja2
Requires-Dist: markdown
Requires-Dist: pytz
Requires-Dist: polib
